{
    "$schema": "https://schema.management.azure.com/schemas/2019-04-01/deploymentParameters.json#",
    "contentVersion": "1.0.0.0",
    "parameters": {
      "vnetName": {
        "value": "myVnet"
      },
      "vnetAddressPrefix": {
        "value": "10.0.0.0/16"
      },
      "frontendSubnetPrefix": {
        "value": "10.0.1.0/24"
      },
      "backendSubnetPrefix": {
        "value": "10.0.2.0/24"
      },
      "dbSubnetPrefix": {
        "value": "10.0.3.0/24"
      },
      "frontendVMSize": {
        "value": "Standard_B1ms"
      },
      "backendVMSize": {
        "value": "Standard_B1ms"
      },
      "adminUsername": {
        "value": "azureuser"
      },
      "adminPassword": {
        "value": "azureuser@123"
      },
      "mySqlAdminPassword": {
        "value": "Mysql@123"
      }
    }
  }
  